<MeshPointDevice time="100" address="00:00:00:00:00:05">
<Statistics
txUnicastData="0"
txUnicastDataBytes="0"
txBroadcastData="0"
txBroadcastDataBytes="0"
rxUnicastData="0"
rxUnicastDataBytes="0"
rxBroadcastData="2"
rxBroadcastDataBytes="56"
fwdUnicastData="371"
fwdUnicastDataBytes="389268"
fwdBroadcastData="2"
fwdBroadcastDataBytes="56"
/>
<Interface BeaconInterval="0.5" Channel="0" Address = "00:00:00:00:00:05">
<Statistics rxBeacons="678" txFrames="1304" txBytes="422378" rxFrames="1396" rxBytes="450682"/>
</Interface>
<Hwmp address="00:00:00:00:00:05"
maxQueueSize="255"
Dot11MeshHWMPmaxPREQretries="3"
Dot11MeshHWMPnetDiameterTraversalTime="0.1024"
Dot11MeshHWMPpreqMinInterval="0.1024"
Dot11MeshHWMPperrMinInterval="0.1024"
Dot11MeshHWMPactiveRootTimeout="5.12"
Dot11MeshHWMPactivePathTimeout="5.12"
Dot11MeshHWMPpathToRootInterval="2.048"
Dot11MeshHWMPrannInterval="5.12"
isRoot="0"
maxTtl="32"
unicastPerrThreshold="32"
unicastPreqThreshold="1"
unicastDataThreshold="1"
doFlag="0"
rfFlag="1">
<Statistics txUnicast="371" txBroadcast="2" txBytes="392292" droppedTtl="0" totalQueued="0" totalDropped="10" initiatedPreq="0" initiatedPrep="23" initiatedPerr="114"/>
<HwmpProtocolMac
address ="00:00:00:00:00:05">
<Statistics txPreq= "154"
txPrep="124"
txPerr="149"
rxPreq="228"
rxPrep="113"
rxPerr="101"
txMgt="427"
txMgtBytes="14408"
rxMgt="442"
rxMgtBytes="15274"
txData="373"
txDataBytes="392308"
rxData="387"
rxDataBytes="403052"/>
</HwmpProtocolMac>
</Hwmp>
<PeerManagementProtocol>
<Statistics linksTotal="4" linksOpened="131" linksClosed="127"/>
<PeerManagementProtocolMac address="00:00:00:00:00:05">
<Statistics txOpen="175"
txConfirm="133"
txClose="214"
rxOpen="177"
rxConfirm="132"
rxClose="214"
dropped="18"
brokenMgt="0"
txMgt="522"
txMgtBytes="13844"
rxMgt="523"
rxMgtBytes="12834"
beaconShift="98"/>
</PeerManagementProtocolMac>
<PeerLink
localAddress="00:00:00:00:00:05"
peerInterfaceAddress="00:00:00:00:00:04"
peerMeshPointAddress="00:00:00:00:00:04"
metric="104"
lastBeacon="99.5771"
localLinkId="169"
peerLinkId="145"
assocId="168"
/>
<PeerLink
localAddress="00:00:00:00:00:05"
peerInterfaceAddress="00:00:00:00:00:02"
peerMeshPointAddress="00:00:00:00:00:02"
metric="233"
lastBeacon="99.5879"
localLinkId="172"
peerLinkId="133"
assocId="171"
/>
<PeerLink
localAddress="00:00:00:00:00:05"
peerInterfaceAddress="00:00:00:00:00:08"
peerMeshPointAddress="00:00:00:00:00:08"
metric="150"
lastBeacon="99.9771"
localLinkId="173"
peerLinkId="137"
assocId="172"
/>
<PeerLink
localAddress="00:00:00:00:00:05"
peerInterfaceAddress="00:00:00:00:00:06"
peerMeshPointAddress="00:00:00:00:00:06"
metric="104"
lastBeacon="99.9946"
localLinkId="174"
peerLinkId="141"
assocId="173"
/>
</PeerManagementProtocol>
</MeshPointDevice>
